tritonclient_futures/__init__.py
tritonclient_futures/sessions.py
tritonclient_futures/utils.py
tritonclient_futures/data/__init__.py
tritonclient_futures/data/inputs.py
tritonclient_futures/data/outputs.py
tritonclient_futures/futures/__init__.py
tritonclient_futures-0.9.0.dist-info/LICENSE
tritonclient_futures-0.9.0.dist-info/METADATA
tritonclient_futures-0.9.0.dist-info/WHEEL
tritonclient_futures-0.9.0.dist-info/top_level.txt
tritonclient_futures-0.9.0.dist-info/RECORD
