Metadata-Version: 2.1
Name: tritonclient-futures
Version: 0.9.0
Summary: 基于python标准库concurrent & requests封装tritonclient
Home-page: 
Author: NICHOLAS WU
Author-email: nicholas_wu@aliyun.com
License: MIT
Platform: UNKNOWN
Requires-Python: >=3.8
License-File: LICENSE
Requires-Dist: tritonclient
Requires-Dist: requests
